AkitaCode/__init__.py
AkitaCode/bd.py
AkitaCode/canbus.py
AkitaCode/conditionals.py
AkitaCode/data.py
AkitaCode/document.py
AkitaCode/frame.py
AkitaCode/information.py
AkitaCode/instances.py
AkitaCode/keys.py
AkitaCode/line.py
AkitaCode/line_state_machine.py
AkitaCode/mask.py
AkitaCode/numerics.py
AkitaCode/protocol.py
AkitaCode/situation.py
AkitaCode-2.1.dist-info/LICENSE
AkitaCode-2.1.dist-info/METADATA
AkitaCode-2.1.dist-info/WHEEL
AkitaCode-2.1.dist-info/top_level.txt
AkitaCode-2.1.dist-info/RECORD
