Metadata-Version: 2.1
Name: AkitaCode
Version: 2.1
Summary: The AkitaCode parser and compiler.
Home-page: https://github.com/alexamatausa/akitacode
Author: Àlex Amat Abad
Author-email: amatabadalex@gmail.com
License: MPL
License-File: LICENSE
Requires-Dist: python-can (==4.2.2)
